exception_logger/__init__.py
exception_logger/apps.py
exception_logger/forms.py
exception_logger/signals.py
exception_logger/utils.py
exception_logger/admin/__init__.py
exception_logger/admin/celery_exception.py
exception_logger/admin/exception.py
exception_logger/admin/request_time.py
exception_logger/locale/en/LC_MESSAGES/django.mo
exception_logger/locale/ru/LC_MESSAGES/django.mo
exception_logger/middlewares/__init__.py
exception_logger/middlewares/exception_logger.py
exception_logger/middlewares/request_time.py
exception_logger/migrations/0001_initial.py
exception_logger/migrations/0002_alter_exceptionmodel_exception.py
exception_logger/migrations/__init__.py
exception_logger/models/__init__.py
exception_logger/models/celery_exception.py
exception_logger/models/enums.py
exception_logger/models/exception.py
exception_logger/models/request_time.py
django_exception_logger-0.1.5.dist-info/LICENSE
django_exception_logger-0.1.5.dist-info/METADATA
django_exception_logger-0.1.5.dist-info/WHEEL
django_exception_logger-0.1.5.dist-info/top_level.txt
django_exception_logger-0.1.5.dist-info/RECORD
